Metadata-Version: 2.4
Name: mseep-aws-security-mcp
Version: 0.1.1
Summary: AWS Security MCP - A comprehensive AWS security inspection and remediation tool
Author-email: mseep <support@skydeck.ai>
License: MIT
Classifier: Development Status :: 4 - Beta
Classifier: Intended Audience :: Developers
Classifier: Intended Audience :: System Administrators
Classifier: License :: OSI Approved :: MIT License
Classifier: Programming Language :: Python :: 3
Classifier: Programming Language :: Python :: 3.11
Classifier: Topic :: Security
Classifier: Topic :: System :: Systems Administration
Requires-Python: >=3.11
License-File: LICENSE
Requires-Dist: boto3>=1.28.0
Requires-Dist: fastapi>=0.100.0
Requires-Dist: uvicorn>=0.22.0
Requires-Dist: pydantic>=2.0.0
Requires-Dist: python-dotenv>=1.0.0
Requires-Dist: httpx>=0.24.1
Provides-Extra: dev
Requires-Dist: pytest>=7.3.1; extra == "dev"
Requires-Dist: pytest-asyncio>=0.21.0; extra == "dev"
Requires-Dist: pytest-cov>=4.1.0; extra == "dev"
Requires-Dist: black>=23.3.0; extra == "dev"
Requires-Dist: isort>=5.12.0; extra == "dev"
Requires-Dist: mypy>=1.3.0; extra == "dev"
Requires-Dist: types-boto3>=1.0.2; extra == "dev"
Dynamic: license-file
